{
	"tags": null,
	"position": [
		107.90132141113281,
		-4.3357010781619465e-7,
		-8.526512829121202e-14
	],
	"rotation": [
		0,
		0,
		0
	],
	"rotationQuaternion": [
		8.673617379884035e-19,
		0,
		0,
		1
	],
	"scaling": [
		1,
		1,
		1
	],
	"billboardMode": 0,
	"scalingDeterminant": 1,
	"infiniteDistance": false,
	"ignoreNonUniformScaling": false,
	"reIntegrateRotationIntoRotationQuaternion": false,
	"name": "shark.RootNode.0.skeletal.3.shark_root.4.Spine1.13.Spine2.14.Spine3.15.Spine4.16.Spine5.17.Spine6.18.Spine7.19",
	"id": "65c7e949-4e2d-4f09-ad32-040c2ba49691",
	"state": "",
	"metadata": {
		"gltf": {
			"pointers": [
				"/nodes/23"
			],
			"editorDone": true
		}
	},
	"type": "TransformNode",
	"parentId": "8646a575-0e63-45ec-a253-35640b2f50dc",
	"localMatrix": {
		"0": 1,
		"1": 0,
		"2": 0,
		"3": 0,
		"4": 0,
		"5": 1,
		"6": 0,
		"7": 0,
		"8": 0,
		"9": 0,
		"10": 1,
		"11": 0,
		"12": 0,
		"13": 0,
		"14": 0,
		"15": 1
	},
	"isEnabled": true
}