{
	"tags": null,
	"position": [
		245.49778747558594,
		-66.95172119140625,
		-0.013665108941495419
	],
	"rotation": [
		0,
		0,
		0
	],
	"rotationQuaternion": [
		0,
		0,
		0,
		1
	],
	"scaling": [
		1,
		1,
		1
	],
	"billboardMode": 0,
	"scalingDeterminant": 1,
	"infiniteDistance": false,
	"ignoreNonUniformScaling": false,
	"reIntegrateRotationIntoRotationQuaternion": false,
	"name": "Upper_Teeth.12",
	"id": "dc21d9bc-ec89-4aba-bf81-b958c17f7a78",
	"state": "",
	"metadata": {
		"gltf": {
			"pointers": [
				"/nodes/17"
			],
			"editorDone": true
		}
	},
	"type": "TransformNode",
	"parentId": "96ba895e-96f3-4510-9143-632839c9eef5",
	"localMatrix": {
		"0": 1,
		"1": 0,
		"2": 0,
		"3": 0,
		"4": 0,
		"5": 1,
		"6": 0,
		"7": 0,
		"8": 0,
		"9": 0,
		"10": 1,
		"11": 0,
		"12": 0,
		"13": 0,
		"14": 0,
		"15": 1
	},
	"isEnabled": true
}